json2gbnf/__init__.py
json2gbnf/json2gbnf.py
json2gbnf/json2gbnf_test.py
json2gbnf/js/index.js
json2gbnf-0.0.4.dist-info/LICENSE
json2gbnf-0.0.4.dist-info/METADATA
json2gbnf-0.0.4.dist-info/WHEEL
json2gbnf-0.0.4.dist-info/top_level.txt
json2gbnf-0.0.4.dist-info/RECORD
